{
  "db_name": "PostgreSQL",
  "query": "\nSELECT id, name, attributes, created_at, updated_at\nFROM user_data_certificates_certificate_templates\nWHERE user_id = $1 AND id = $2\n                ",
  "describe": {
    "columns": [
      {
        "ordinal": 0,
        "name": "id",
        "type_info": "Uuid"
      },
      {
        "ordinal": 1,
        "name": "name",
        "type_info": "Text"
      },
      {
        "ordinal": 2,
        "name": "attributes",
        "type_info": "Bytea"
      },
      {
        "ordinal": 3,
        "name": "created_at",
        "type_info": "Timestamptz"
      },
      {
        "ordinal": 4,
        "name": "updated_at",
        "type_info": "Timestamptz"
      }
    ],
    "parameters": {
      "Left": [
        "Uuid",
        "Uuid"
      ]
    },
    "nullable": [
      false,
      false,
      false,
      false,
      false
    ]
  },
  "hash": "b8c1d7fb1b4e0572abe4810e77361ee603c2937d643a47e268da19fa56ea0be9"
}
